mpayments/__init__.py
mpayments/admin.py
mpayments/apps.py
mpayments/helpers.py
mpayments/models.py
mpayments/serializers.py
mpayments/tests.py
mpayments/views.py
mpayments/lipa_na_mpesa/__init__.py
mpayments/lipa_na_mpesa/lipa_na_mpesa.py
mpayments/lipa_na_mpesa/utils.py
mpayments/migrations/0001_initial.py
mpayments/migrations/__init__.py
dj_mpesa_payment-1.0.0.dist-info/METADATA
dj_mpesa_payment-1.0.0.dist-info/WHEEL
dj_mpesa_payment-1.0.0.dist-info/top_level.txt
dj_mpesa_payment-1.0.0.dist-info/RECORD
